_rfstools/__init__.py
_rfstools/arg_parser.py
_rfstools/arg_processor.py
rfslib/__init__.py
rfslib/abstract_pconnection.py
rfslib/fs_pconnection.py
rfslib/ftp_pconnection.py
rfslib/path_utils.py
rfslib/pconnection_settings.py
rfslib/pglobber.py
rfslib/pinstance.py
rfslib/sftp_pconnection.py
rfslib/smb12_pconnection.py
rfslib/smb23_pconnection.py
rfstools-1.8.3.data/scripts/pcp
rfstools-1.8.3.data/scripts/pexist
rfstools-1.8.3.data/scripts/pisdir
rfstools-1.8.3.data/scripts/pls
rfstools-1.8.3.data/scripts/pmkdir
rfstools-1.8.3.data/scripts/pmv
rfstools-1.8.3.data/scripts/prm
rfstools-1.8.3.data/scripts/prmdir
rfstools-1.8.3.data/scripts/pstat
rfstools-1.8.3.data/scripts/ptouch
rfstools-1.8.3.dist-info/LICENSE
rfstools-1.8.3.dist-info/METADATA
rfstools-1.8.3.dist-info/WHEEL
rfstools-1.8.3.dist-info/top_level.txt
rfstools-1.8.3.dist-info/RECORD
