Metadata-Version: 2.1
Name: rfstools
Version: 1.8.3
Summary: Remote file system tools for data manipulation between remote /and local host/ (cp, mv, ls, rm,..)
Home-page: https://git.profinit.eu/pstastny/rfstools
Author: Přemysl Šťastný
Author-email: p-w@stty.cz
License-File: LICENSE
Requires-Dist: ConfigArgParse <2,>=1.4.1
Requires-Dist: texttable <2,>=1.6.4
Requires-Dist: pysmb <2,>=1.2.7
Requires-Dist: paramiko <4,>=2.7.2
Requires-Dist: smbprotocol <2,>=1.6.1
Requires-Dist: ftputil <6,>=5.0.1
